pynator/__init__.py
pynator/pynator.py
pynator-0.1.1.dist-info/LICENSE
pynator-0.1.1.dist-info/METADATA
pynator-0.1.1.dist-info/WHEEL
pynator-0.1.1.dist-info/RECORD
