Metadata-Version: 2.1
Name: pynator
Version: 0.1.1
Summary: 
Author: hackirby
Author-email: 145487845+hackirby@users.noreply.github.com
Requires-Python: >=3.11,<4.0
Classifier: Programming Language :: Python :: 3
Classifier: Programming Language :: Python :: 3.11
Requires-Dist: requests (>=2.31.0,<3.0.0)
